nonebot_plugin_ai_timetable/__init__.py
nonebot_plugin_ai_timetable/config.py
nonebot_plugin_ai_timetable/data_manager.py
nonebot_plugin_ai_timetable/manager.py
nonebot_plugin_ai_timetable/migrations/f67eb52d6a0f_init.py
nonebot_plugin_ai_timetable/model.py
nonebot_plugin_ai_timetable/reminder.py
nonebot_plugin_ai_timetable-0.4.1.dist-info/LICENSE
nonebot_plugin_ai_timetable-0.4.1.dist-info/METADATA
nonebot_plugin_ai_timetable-0.4.1.dist-info/WHEEL
nonebot_plugin_ai_timetable-0.4.1.dist-info/RECORD
