Metadata-Version: 2.1
Name: nonebot-plugin-ai-timetable
Version: 0.4.1
Summary: 小爱课程表
Author: maoxiog
Author-email: 674550338@qq.com
Requires-Python: >=3.8,<4.0
Classifier: Programming Language :: Python :: 3
Classifier: Programming Language :: Python :: 3.8
Classifier: Programming Language :: Python :: 3.9
Classifier: Programming Language :: Python :: 3.10
Classifier: Programming Language :: Python :: 3.11
Classifier: Programming Language :: Python :: 3.12
Requires-Dist: httpx (>=0.20.0,<1.0.0)
Requires-Dist: nonebot-plugin-alconna (>=0.40.1,<1.0.0)
Requires-Dist: nonebot-plugin-apscheduler (>=0.2.0,<1.0.0)
Requires-Dist: nonebot-plugin-htmlrender (>=0.3.0,<0.4.0)
Requires-Dist: nonebot-plugin-orm (>=0.7.1)
Requires-Dist: nonebot2 (>=2.2.0,<3.0.0)
